ogcore/OGcorePlots.mplstyle
ogcore/SS.py
ogcore/TPI.py
ogcore/__init__.py
ogcore/_version.py
ogcore/aggregates.py
ogcore/config.py
ogcore/constants.py
ogcore/default_parameters.json
ogcore/demographics.py
ogcore/elliptical_u_est.py
ogcore/execute.py
ogcore/firm.py
ogcore/fiscal.py
ogcore/household.py
ogcore/model_variables.json
ogcore/output_plots.py
ogcore/output_tables.py
ogcore/parameter_plots.py
ogcore/parameter_tables.py
ogcore/parameters.py
ogcore/pensions.py
ogcore/tax.py
ogcore/txfunc.py
ogcore/utils.py
ogcore-0.15.3.dist-info/licenses/LICENSE
ogcore-0.15.3.dist-info/METADATA
ogcore-0.15.3.dist-info/WHEEL
ogcore-0.15.3.dist-info/top_level.txt
ogcore-0.15.3.dist-info/RECORD
