Metadata-Version: 2.4
Name: ogcore
Version: 0.15.3
Summary: A general equilibrium overlapping generations model for fiscal policy analysis
Home-page: https://github.com/PSLmodels/OG-Core/
Download-URL: https://github.com/PLSmodels/OG-Core/
Author: Jason DeBacker and Richard W. Evans
License: CC0 1.0 Universal (CC0 1.0) Public Domain Dedication
Project-URL: Issue Tracker, https://github.com/PSLmodels/OG-Core/issues
Classifier: Development Status :: 2 - Pre-Alpha
Classifier: Intended Audience :: Developers
Classifier: Natural Language :: English
Classifier: License :: CC0 1.0 Universal (CC0 1.0) Public Domain Dedication
Classifier: Operating System :: OS Independent
Classifier: Programming Language :: Python
Classifier: Programming Language :: Python :: 3
Classifier: Programming Language :: Python :: 3.11
Classifier: Programming Language :: Python :: 3.12
Classifier: Programming Language :: Python :: 3.13
Classifier: Topic :: Software Development :: Libraries :: Python Modules
Requires-Python: >=3.11, <3.14
License-File: LICENSE
Requires-Dist: numpy
Requires-Dist: scipy>=1.7.1
Requires-Dist: pandas>=1.2.5
Requires-Dist: numba
Requires-Dist: matplotlib
Requires-Dist: dask>=2.30.0
Requires-Dist: distributed>=2.30.1
Requires-Dist: paramtools>=0.20.0
Requires-Dist: requests
Requires-Dist: pip
Requires-Dist: pygam
Dynamic: author
Dynamic: classifier
Dynamic: description
Dynamic: description-content-type
Dynamic: download-url
Dynamic: home-page
Dynamic: license
Dynamic: license-file
Dynamic: project-url
Dynamic: requires-dist
Dynamic: requires-python
Dynamic: summary
